darkskyutils/__init__.py
darkskyutils/command.py
darkskyutils/config.py
darkskyutils/encrypt.py
darkskyutils/file.py
darkskyutils/logger.py
darkskyutils/tcp.py
darkskyutils/udp.py
darkskyutils-0.1.0.dist-info/LICENSE
darkskyutils-0.1.0.dist-info/METADATA
darkskyutils-0.1.0.dist-info/WHEEL
darkskyutils-0.1.0.dist-info/top_level.txt
darkskyutils-0.1.0.dist-info/RECORD
