Metadata-Version: 2.1
Name: darkskyutils
Version: 0.1.0
Summary: Useful tool classes including log, config, tcp, etc.
Home-page: https://github.com/DarkskyX15/darkskyutils
Author: Darksky
Author-email: 2290168728@qq.com
License: BSD License
Platform: UNKNOWN
Classifier: Programming Language :: Python :: 3
Classifier: License :: OSI Approved :: BSD License
Classifier: Operating System :: OS Independent
Requires: pycryptodome
Requires-Python: >=3.9
License-File: LICENSE
